aws_cognito_cli/VERSION
aws_cognito_cli/__init__.py
aws_cognito_cli/aws_cognito_cli.py
aws_cognito_cli/cli.py
aws_cognito_cli-0.2.0.dist-info/AUTHORS.rst
aws_cognito_cli-0.2.0.dist-info/LICENSE
aws_cognito_cli-0.2.0.dist-info/METADATA
aws_cognito_cli-0.2.0.dist-info/WHEEL
aws_cognito_cli-0.2.0.dist-info/entry_points.txt
aws_cognito_cli-0.2.0.dist-info/top_level.txt
aws_cognito_cli-0.2.0.dist-info/RECORD
